LICENSE
MANIFEST.in
README.rst
setup.py
slacksend.py
slacksend.egg-info/PKG-INFO
slacksend.egg-info/SOURCES.txt
slacksend.egg-info/dependency_links.txt
slacksend.egg-info/entry_points.txt
slacksend.egg-info/requires.txt
slacksend.egg-info/top_level.txt