Metadata-Version: 1.1
Name: slacksend
Version: 0.1
Summary: Sends messages to slack's incoming webhooks via CLI
Home-page: https://github.com/mtorromeo/slacksend
Author: Massimiliano Torromeo
Author-email: massimiliano.torromeo@gmail.com
License: MIT License
Download-URL: https://github.com/mtorromeo/slacksend/tarball/v0.1
Platform: UNKNOWN
Classifier: Programming Language :: Python
Classifier: Programming Language :: Python :: 3.4
Classifier: License :: OSI Approved :: MIT License
Classifier: Intended Audience :: System Administrators
Classifier: Operating System :: POSIX :: Linux
Classifier: Natural Language :: English
Classifier: Topic :: Utilities
